vectorx/__init__.py
vectorx/index.py
vectorx/vectorx.py
vectorx/libvx/libvx_arm64.dylib
vecx/__init__.py
vecx/crypto.py
vecx/exceptions.py
vecx/hybrid.py
vecx/index.py
vecx/libvx.py
vecx/user.py
vecx/utils.py
vecx/vectorx.py
vecx/vecx_pb2.py
vecx/libvx/libvx_aarch64.so
vecx/libvx/libvx_arm64.dylib
vecx/libvx/libvx_arm64.so
vecx/libvx/libvx_x86_64.dll
vecx/libvx/libvx_x86_64.dylib
vecx/libvx/libvx_x86_64.so
vecx-0.33.1.dist-info/LICENSE
vecx-0.33.1.dist-info/METADATA
vecx-0.33.1.dist-info/WHEEL
vecx-0.33.1.dist-info/top_level.txt
vecx-0.33.1.dist-info/RECORD
