Metadata-Version: 2.1
Name: vecx
Version: 0.33.1
Summary: Encrypted Vector Database for Secure and Fast ANN Searches
Home-page: https://vectorxdb.ai
Author: LaunchX Labs
Author-email: support@vectorxdb.ai
Classifier: Programming Language :: Python :: 3
Classifier: License :: OSI Approved :: MIT License
Classifier: Operating System :: OS Independent
Requires-Python: >=3.6
License-File: LICENSE
Requires-Dist: requests>=2.28.0
Requires-Dist: numpy>=2.2.4
Requires-Dist: msgpack>=1.1.0
Requires-Dist: cffi>=1.17.1
